{
 "platform": "카드고릴라",
 "scope": "credit",
 "chart": "고릴라TOP100",
 "period": "2026.06.15~2026.06.21(주간)",
 "captured": "2026-06-21",
 "note": "카드고릴라 신용카드 인기순위 TOP100. 사실 데이터(순위·카드명·카드사·최대 혜택/캐시백 금액)만 수집. 소개·마케팅 문구 미수집.",
 "items": [
  {"rank":1,"name":"삼성 iD SELECT ALL 카드","issuer":"삼성카드","amount":"최대 49.4만원"},
  {"rank":2,"name":"신한카드 Mr.Life","issuer":"신한카드","amount":"최대 57.9만원"},
  {"rank":3,"name":"삼성카드 & MILEAGE PLATINUM (스카이패스)","issuer":"삼성카드","amount":"최대 117만원"},
  {"rank":4,"name":"굿데이카드","issuer":"KB국민카드","amount":"최대 86만원 캐시백"},
  {"rank":5,"name":"카드의정석2","issuer":"우리카드","amount":"최대 78만원"},
  {"rank":6,"name":"American Express Gold Card Edition2","issuer":"현대카드","amount":"최대 50만원 캐시백"},
  {"rank":7,"name":"LOCA LIKIT 2.0","issuer":"롯데카드","amount":"최대 67만원"},
  {"rank":8,"name":"KB국민 My WE:SH 카드","issuer":"KB국민카드","amount":"최대 86만원 캐시백"},
  {"rank":9,"name":"현대카드 M","issuer":"현대카드","amount":"최대 68.5만원 캐시백"},
  {"rank":10,"name":"카드의정석 SHOPPING+","issuer":"우리카드","amount":"최대 75만원"},
  {"rank":11,"name":"삼성 iD SELECT ON 카드","issuer":"삼성카드","amount":"최대 49.4만원"},
  {"rank":12,"name":"KB NEED Pay 카드","issuer":"KB국민카드","amount":"최대 86만원 캐시백"},
  {"rank":13,"name":"신한카드 Discount Plan+","issuer":"신한카드","amount":"최대 78.9만원"},
  {"rank":14,"name":"LOCA LIKIT 1.5","issuer":"롯데카드","amount":"최대 67만원"},
  {"rank":15,"name":"트래블로그+(플러스) 신용카드","issuer":"하나카드","amount":"최대 57만원"},
  {"rank":16,"name":"삼성카드 taptap O","issuer":"삼성카드","amount":""},
  {"rank":17,"name":"삼성 iD SIMPLE 카드","issuer":"삼성카드","amount":""},
  {"rank":18,"name":"신한카드 처음(ANNIVERSE)","issuer":"신한카드","amount":"최대 57.9만원"},
  {"rank":19,"name":"LOCA 365 카드","issuer":"롯데카드","amount":"최대 64만원"},
  {"rank":20,"name":"현대카드 Summit","issuer":"현대카드","amount":"25만원 캐시백"},
  {"rank":21,"name":"KB YOU Prime 카드","issuer":"KB국민카드","amount":"최대 86만원 캐시백"},
  {"rank":22,"name":"THE iD. 1st","issuer":"삼성카드","amount":"기존회원 최대 12.4만원"},
  {"rank":23,"name":"신한카드 Deep Oil","issuer":"신한카드","amount":"최대 57.9만원"},
  {"rank":24,"name":"우리카드 MILE&POINT","issuer":"우리카드","amount":"최대 78만원"},
  {"rank":25,"name":"taptap DIGITAL","issuer":"삼성카드","amount":""},
  {"rank":26,"name":"현대카드ZERO Edition3(할인형)","issuer":"현대카드","amount":"1.5만원 캐시백"},
  {"rank":27,"name":"대한항공카드 the First Edition2","issuer":"현대카드","amount":"최대 89만원 캐시백"},
  {"rank":28,"name":"삼성 iD GLOBAL 카드","issuer":"삼성카드","amount":""},
  {"rank":29,"name":"올바른 FLEX 카드","issuer":"NH농협카드","amount":"최대 17.5만원 캐시백"},
  {"rank":30,"name":"대한항공카드 300","issuer":"현대카드","amount":"최대 79만원 캐시백"},
  {"rank":31,"name":"KB YOU Wish 카드","issuer":"KB국민카드","amount":"최대 86만원 캐시백"},
  {"rank":32,"name":"우리카드 7CORE","issuer":"우리카드","amount":"최대 78만원"},
  {"rank":33,"name":"LOCA LIKIT 1.2","issuer":"롯데카드","amount":""},
  {"rank":34,"name":"JADE Classic","issuer":"하나카드","amount":""},
  {"rank":35,"name":"신한카드 Simple Plan+","issuer":"신한카드","amount":"최대 78.9만원"},
  {"rank":36,"name":"카드의정석 EVERY MILE SKYPASS","issuer":"우리카드","amount":"3.9만원 캐시백"},
  {"rank":37,"name":"디지로카 London","issuer":"롯데카드","amount":"최대 64만원"},
  {"rank":38,"name":"the Orange","issuer":"현대카드","amount":"25만원 캐시백"},
  {"rank":39,"name":"카드의정석2 EVERY DISCOUNT","issuer":"우리카드","amount":"최대 75만원"},
  {"rank":40,"name":"K-패스 (신용)","issuer":"IBK기업은행","amount":"최대 12.5만원 캐시백"},
  {"rank":41,"name":"카드의정석2 SUPER","issuer":"우리카드","amount":""},
  {"rank":42,"name":"신한카드 Point Plan","issuer":"신한카드","amount":"최대 57.9만원"},
  {"rank":43,"name":"디지로카 Las Vegas","issuer":"롯데카드","amount":"최대 64만원"},
  {"rank":44,"name":"신한카드 Air One","issuer":"신한카드","amount":"최대 78.9만원"},
  {"rank":45,"name":"신한카드 The BEST-F","issuer":"신한카드","amount":""},
  {"rank":46,"name":"the OPUS silver","issuer":"우리카드","amount":"최대 78만원"},
  {"rank":47,"name":"대한항공카드 060","issuer":"현대카드","amount":"최대 73만원 캐시백"},
  {"rank":48,"name":"THE 1 (스카이패스)","issuer":"삼성카드","amount":""},
  {"rank":49,"name":"zgm 할인카드","issuer":"NH농협카드","amount":"연회비 캐시백"},
  {"rank":50,"name":"대한항공카드 120","issuer":"현대카드","amount":"최대 76만원 캐시백"},
  {"rank":51,"name":"쿠팡 와우카드","issuer":"KB국민카드","amount":""},
  {"rank":52,"name":"삼성 iD ON 카드","issuer":"삼성카드","amount":"온라인 신규회원 연회비 100% 캐시백"},
  {"rank":53,"name":"클래시 트래블카드","issuer":"NH농협카드","amount":"연회비 캐시백"},
  {"rank":54,"name":"MG+ BLACK 하나카드","issuer":"MG새마을금고","amount":""},
  {"rank":55,"name":"American Express Green Card Edition2","issuer":"현대카드","amount":"최대 25만원 캐시백"},
  {"rank":56,"name":"하나 스카이패스 아멕스 플래티늄 카드","issuer":"하나카드","amount":""},
  {"rank":57,"name":"IBK포인트(신용)","issuer":"IBK기업은행","amount":"최대 12.5만원 캐시백"},
  {"rank":58,"name":"가온올림카드(실속형)","issuer":"KB국민카드","amount":""},
  {"rank":59,"name":"현대카드 ZERO Up(할인형)","issuer":"현대카드","amount":"3만원 캐시백"},
  {"rank":60,"name":"메리어트 본보이 더 베스트 신한카드","issuer":"신한카드","amount":""},
  {"rank":61,"name":"신한카드 Globus","issuer":"신한카드","amount":"최대 55.9만원 + 공항라운지 무료입장권"},
  {"rank":62,"name":"zgm.streaming카드","issuer":"NH농협카드","amount":"최대 17.5만원 캐시백"},
  {"rank":63,"name":"현대카드T","issuer":"현대카드","amount":"1.5만원 캐시백"},
  {"rank":64,"name":"zgm.play카드","issuer":"NH농협카드","amount":"최대 17.5만원 캐시백"},
  {"rank":65,"name":"IBK포인트3.8(신용)","issuer":"IBK기업은행","amount":"최대 12.5만원 캐시백"},
  {"rank":66,"name":"DA카드의정석Ⅱ","issuer":"우리카드","amount":"1.2만원 캐시백"},
  {"rank":67,"name":"에너지플러스 현대카드","issuer":"현대카드","amount":"최대 60만원 캐시백"},
  {"rank":68,"name":"네이버 현대카드 Edition2","issuer":"현대카드","amount":""},
  {"rank":69,"name":"BC 바로 클리어 플러스","issuer":"BC카드","amount":""},
  {"rank":70,"name":"원더카드 2.0 FREE+","issuer":"하나카드","amount":""},
  {"rank":71,"name":"HERITAGE Smart [대한항공 마일리지형]","issuer":"KB국민카드","amount":""},
  {"rank":72,"name":"현대카드O","issuer":"현대카드","amount":"1.5만원 캐시백"},
  {"rank":73,"name":"I-Mileage (대한항공)","issuer":"IBK기업은행","amount":"최대 4.2만원 캐시백"},
  {"rank":74,"name":"카드의정석 I&U+","issuer":"우리카드","amount":"최대 75만원"},
  {"rank":75,"name":"WE:SH Travel","issuer":"KB국민카드","amount":""},
  {"rank":76,"name":"네이버페이 taptap","issuer":"삼성카드","amount":""},
  {"rank":77,"name":"신한카드 The CLASSIC+","issuer":"신한카드","amount":""},
  {"rank":78,"name":"zgm.일본여행중 카드","issuer":"NH농협카드","amount":""},
  {"rank":79,"name":"신한카드 Point Plan+","issuer":"신한카드","amount":"최대 34.9만원"},
  {"rank":80,"name":"토스뱅크 하나카드 Day","issuer":"하나카드","amount":""},
  {"rank":81,"name":"I-ALL","issuer":"IBK기업은행","amount":"최대 12.5만원 캐시백"},
  {"rank":82,"name":"LOCA LIKIT Play","issuer":"롯데카드","amount":"최대 59만원"},
  {"rank":83,"name":"카드의정석 TEN","issuer":"우리카드","amount":"최대 75만원"},
  {"rank":84,"name":"힐튼 아너스 아멕스 프리미엄","issuer":"롯데카드","amount":""},
  {"rank":85,"name":"THE iD. PLATINUM(포인트)","issuer":"삼성카드","amount":""},
  {"rank":86,"name":"LOCA Professional","issuer":"롯데카드","amount":""},
  {"rank":87,"name":"BeV V카드(스카이패스형)","issuer":"KB국민카드","amount":""},
  {"rank":88,"name":"현대카드 MX Black Edition2","issuer":"현대카드","amount":"20만원 캐시백"},
  {"rank":89,"name":"카드의정석2 EVERY POINT","issuer":"우리카드","amount":"최대 75만원"},
  {"rank":90,"name":"디지로카 Paris","issuer":"롯데카드","amount":"최대 64만원"},
  {"rank":91,"name":"BC 바로 Air Max 카드","issuer":"BC카드","amount":"연회비 100% 캐시백"},
  {"rank":92,"name":"zgm.the pay카드","issuer":"NH농협카드","amount":"연회비 캐시백"},
  {"rank":93,"name":"삼성 iD ALL 카드","issuer":"삼성카드","amount":""},
  {"rank":94,"name":"올바른 NEW HAVE카드","issuer":"NH농협카드","amount":"연회비 캐시백"},
  {"rank":95,"name":"현대카드ZERO Edition3(포인트형)","issuer":"현대카드","amount":"1.5만원 캐시백"},
  {"rank":96,"name":"The Aureum(더 아우름)카드","issuer":"Sh수협은행","amount":"최대 20만원"},
  {"rank":97,"name":"JADE Prime","issuer":"하나카드","amount":""},
  {"rank":98,"name":"Haru(Hoshino Resorts)","issuer":"신한카드","amount":"최대 34.9만원"},
  {"rank":99,"name":"삼성 iD PLUG-IN 카드","issuer":"삼성카드","amount":""},
  {"rank":100,"name":"American Express The Platinum Card Edition2","issuer":"현대카드","amount":""}
 ]
}
